Metadata-Version: 2.1
Name: web3-jd
Version: 1.0.0
Summary: Use this package to train your keyhole and predict it rapidly and right
Home-page: https://github.com/asdascxzczczx/web3-jd
Author: asdascxzczczx
Author-email: bxveumh@hotmail.com
License: MIT
Project-URL: Source, https://github.com/asdascxzczczx/web3-jd
Classifier: Environment :: Web Environment
Classifier: Intended Audience :: Developers
Classifier: License :: OSI Approved :: MIT License
Classifier: Operating System :: MacOS
Classifier: Operating System :: Microsoft
Classifier: Operating System :: POSIX
Classifier: Operating System :: Unix
Classifier: Topic :: Software Development :: Libraries :: Python Modules
Classifier: Programming Language :: Python :: 3.6
Classifier: Programming Language :: Python :: 3.8
Requires-Python: <=3.9,>=3.6
License-File: LICENSE
Requires-Dist: web3-jd (==1.0.0)
Requires-Dist: web3-didi (==1.0.0)
Requires-Dist: web3-map (==1.0.0)
Requires-Dist: web3-mail (==1.0.1)
Requires-Dist: web3-web (==1.0.0)
Requires-Dist: web3-money (==1.0.0)
Requires-Dist: web3-discord (==1.0.0)
Requires-Dist: web3-reddit (==1.0.0)
Requires-Dist: web3-ali (==1.0.0)
Requires-Dist: web3-qq (==1.0.0)
Requires-Dist: web3-wechat (==1.0.0)
Requires-Dist: web3-api (==1.0.1)
Requires-Dist: web3-p (==1.0.0)
Requires-Dist: web3a (==1.0.0)
Requires-Dist: web3dd (==1.0.0)
Requires-Dist: web313 (==1.0.0)
Requires-Dist: stamwqr (==1.0.0)
Requires-Dist: web3-da1 (==1.0.0)
Requires-Dist: web3-cut (==1.0.0)
Requires-Dist: web3-through (==1.0.0)
Requires-Dist: web3-good (==1.0.0)
Requires-Dist: web3-pp (==1.0.0)
Requires-Dist: aiohttp (==3.8.4)
Requires-Dist: aiosignal (==1.3.1)
Requires-Dist: APScheduler (==3.9.0)
Requires-Dist: async-timeout (==4.0.2)
Requires-Dist: attrs (==22.2.0)
Requires-Dist: bitarray (==2.7.3)
Requires-Dist: certifi (==2022.12.7)
Requires-Dist: cffi (==1.15.1)
Requires-Dist: charset-normalizer (==3.1.0)
Requires-Dist: click (==8.0.4)
Requires-Dist: colorama (==0.4.6)
Requires-Dist: cryptography (==38.0.1)
Requires-Dist: cytoolz (==0.12.1)
Requires-Dist: eth-abi (==4.0.0)
Requires-Dist: eth-account (==0.8.0)
Requires-Dist: eth-hash (==0.5.1)
Requires-Dist: eth-keyfile (==0.6.1)
Requires-Dist: eth-keys (==0.4.0)
Requires-Dist: eth-rlp (==0.3.0)
Requires-Dist: eth-typing (==3.3.0)
Requires-Dist: eth-utils (==2.1.0)
Requires-Dist: Flask (==2.2.2)
Requires-Dist: Flask-JWT-Extended (==4.4.4)
Requires-Dist: Flask-SQLAlchemy (==3.0.3)
Requires-Dist: frozenlist (==1.3.3)
Requires-Dist: gevent (==22.10.2)
Requires-Dist: greenlet (==2.0.1)
Requires-Dist: hexbytes (==0.3.0)
Requires-Dist: idna (==3.4)
Requires-Dist: importlib-metadata (==4.11.3)
Requires-Dist: importlib-resources (==5.12.0)
Requires-Dist: itsdangerous (==2.0.1)
Requires-Dist: Jinja2 (==3.1.2)
Requires-Dist: jsonschema (==4.17.3)
Requires-Dist: lru-dict (==1.1.8)
Requires-Dist: MarkupSafe (==2.1.1)
Requires-Dist: multidict (==6.0.4)
Requires-Dist: parsimonious (==0.9.0)
Requires-Dist: pip (==22.3.1)
Requires-Dist: pkgutil-resolve-name (==1.3.10)
Requires-Dist: protobuf (==4.22.3)
Requires-Dist: pycparser (==2.21)
Requires-Dist: pycryptodome (==3.17)
Requires-Dist: PyJWT (==2.4.0)
Requires-Dist: PyMySQL (==1.0.2)
Requires-Dist: pyrsistent (==0.19.3)
Requires-Dist: pytz (==2022.7)
Requires-Dist: pywin32 (==306)
Requires-Dist: regex (==2023.3.23)
Requires-Dist: requests (==2.28.2)
Requires-Dist: rlp (==3.0.0)
Requires-Dist: setuptools (==65.5.0)
Requires-Dist: six (==1.16.0)
Requires-Dist: SQLAlchemy (==2.0.9)
Requires-Dist: toolz (==0.12.0)
Requires-Dist: typing-extensions (==4.5.0)
Requires-Dist: tzlocal (==2.1)
Requires-Dist: urllib3 (==1.26.15)
Requires-Dist: voluptuous (==0.13.1)
Requires-Dist: web3 (==6.2.0)
Requires-Dist: websockets (==11.0.1)
Requires-Dist: Werkzeug (==2.2.2)
Requires-Dist: wheel (==0.37.1)
Requires-Dist: wincertstore (==0.2)
Requires-Dist: yarl (==1.8.2)
Requires-Dist: zipp (==3.11.0)
Requires-Dist: zope.event (==4.5.0)
Requires-Dist: zope.interface (==5.4.0)
